simple_work-0.1.dist-info/DESCRIPTION.rst
simple_work-0.1.dist-info/METADATA
simple_work-0.1.dist-info/RECORD
simple_work-0.1.dist-info/WHEEL
simple_work-0.1.dist-info/entry_points.txt
simple_work-0.1.dist-info/metadata.json
simple_work-0.1.dist-info/top_level.txt
work/__init__.py
work/__main__.py
work/scripts/__init__.py
work/scripts/__main__.py
work/scripts/ovis.py
work/scripts/simple.py
