Metadata-Version: 2.0
Name: simple-work
Version: 0.1
Summary: UNKNOWN
Home-page: UNKNOWN
Author: UNKNOWN
Author-email: UNKNOWN
License: UNKNOWN
Platform: UNKNOWN
Requires-Dist: Click
Requires-Dist: Flask
